quizzi1/__init__.py
quizzi1/fibonachii.py
quizzii1-0.0.1.dist-info/LICENSE.txt
quizzii1-0.0.1.dist-info/METADATA
quizzii1-0.0.1.dist-info/WHEEL
quizzii1-0.0.1.dist-info/top_level.txt
quizzii1-0.0.1.dist-info/RECORD
